rubka/__init__.py
rubka/api.py
rubka/asynco.py
rubka/button.py
rubka/config.py
rubka/context.py
rubka/decorators.py
rubka/exceptions.py
rubka/filters.py
rubka/helpers.py
rubka/jobs.py
rubka/keyboards.py
rubka/keypad.py
rubka/logger.py
rubka/metadata.py
rubka/rubino.py
rubka/tv.py
rubka/update.py
rubka/utils.py
rubka/adaptorrubka/__init__.py
rubka/adaptorrubka/enums.py
rubka/adaptorrubka/exceptions.py
rubka/adaptorrubka/client/__init__.py
rubka/adaptorrubka/client/client.py
rubka/adaptorrubka/crypto/__init__.py
rubka/adaptorrubka/crypto/crypto.py
rubka/adaptorrubka/methods/__init__.py
rubka/adaptorrubka/methods/methods.py
rubka/adaptorrubka/network/__init__.py
rubka/adaptorrubka/network/helper.py
rubka/adaptorrubka/network/network.py
rubka/adaptorrubka/network/socket.py
rubka/adaptorrubka/sessions/__init__.py
rubka/adaptorrubka/sessions/sessions.py
rubka/adaptorrubka/types/__init__.py
rubka/adaptorrubka/types/socket/__init__.py
rubka/adaptorrubka/types/socket/message.py
rubka/adaptorrubka/utils/__init__.py
rubka/adaptorrubka/utils/configs.py
rubka/adaptorrubka/utils/utils.py
rubka-7.5.1.dist-info/METADATA
rubka-7.5.1.dist-info/WHEEL
rubka-7.5.1.dist-info/entry_points.txt
rubka-7.5.1.dist-info/top_level.txt
rubka-7.5.1.dist-info/RECORD
