Metadata-Version: 2.4
Name: Rubka
Version: 7.5.1
Summary: Rubika: A Python library for interacting with the Rubika Bot API. This library provides an easy-to-use interface to send messages, polls, stickers, media files, manage groups and channels, handle inline keyboards, and implement advanced bot features like subscription management, user authentication, and message handling. Ideal for developers looking to automate and extend their Rubika bots with Python.
Home-page: https://github.com/Mahdy-Ahmadi/Rubka
Download-URL: https://github.com/Mahdy-Ahmadi/rubka/archive/refs/tags/v6.6.4.zip
Author: Mahdi Ahmadi
Author-email: mahdiahmadi.1208@gmail.com
Maintainer: Mahdi Ahmadi
Maintainer-email: mahdiahmadi.1208@gmail.com
License: MIT
Project-URL: Bug Tracker, https://t.me/Dev_servers
Project-URL: Documentation, https://github.com/Mahdy-Ahmadi/rubka/blob/main/README.md
Project-URL: Source Code, https://github.com/Mahdy-Ahmadi/Rubka
Keywords: rubika bot api library chat messaging rubpy pyrubi rubigram rubika_bot rubika_api fast_rub
Classifier: Development Status :: 5 - Production/Stable
Classifier: Intended Audience :: Developers
Classifier: Programming Language :: Python :: 3
Classifier: Programming Language :: Python :: 3.8
Classifier: Programming Language :: Python :: 3.9
Classifier: Programming Language :: Python :: 3.10
Classifier: License :: OSI Approved :: MIT License
Classifier: Operating System :: OS Independent
Classifier: Topic :: Communications :: Chat
Classifier: Topic :: Software Development :: Libraries
Classifier: Natural Language :: Persian
Requires-Python: >=3.6
Requires-Dist: requests
Requires-Dist: websocket-client
Requires-Dist: pycryptodome
Requires-Dist: aiohttp
Requires-Dist: httpx
Requires-Dist: tqdm
Requires-Dist: mutagen
Requires-Dist: markdownify
Requires-Dist: filetype
Requires-Dist: aiofiles
Requires-Dist: deep-translator
Requires-Dist: orjson
Dynamic: author
Dynamic: author-email
Dynamic: classifier
Dynamic: description
Dynamic: description-content-type
Dynamic: download-url
Dynamic: home-page
Dynamic: keywords
Dynamic: license
Dynamic: maintainer
Dynamic: maintainer-email
Dynamic: project-url
Dynamic: requires-dist
Dynamic: requires-python
Dynamic: summary
